pycampus/__about__.py
pycampus/__init__.py
pycampus/main.py
pycampus-0.2.0.dist-info/METADATA
pycampus-0.2.0.dist-info/WHEEL
pycampus-0.2.0.dist-info/entry_points.txt
pycampus-0.2.0.dist-info/licenses/LICENSE
pycampus-0.2.0.dist-info/RECORD
