Metadata-Version: 2.1
Name: pycampus
Version: 0.2.0
Summary: A Python student management program
Project-URL: Homepage, https://github.com/tysonjmak/pycampus
Project-URL: Source, https://github.com/tysonjmak/pycampus
Author-email: Tyson Mak <tysonjmak@gmail.com>
License-File: LICENSE
Classifier: Development Status :: 2 - Pre-Alpha
Classifier: Intended Audience :: End Users/Desktop
Classifier: License :: OSI Approved :: MIT License
Classifier: Natural Language :: English
Classifier: Operating System :: OS Independent
Classifier: Programming Language :: Python :: 3
Classifier: Topic :: Utilities
Requires-Python: >=3.7
Requires-Dist: click
